Modules/IDU/IDU_top.sv
module IDU_top(
    //templated
    input soc_clk,
    input IDU_reset, //flushing
    input [31:0] instruction,
    input [1:0] stage_counter,

    output reg [5:0] Instruction_to_CU   , //CU instruction select. refer to cu_code_ref.md to decode.

    //databusses
    output reg [31:0] imm,
    output reg [4:0] rd, //CU register sel
    output reg [4:0] rs1,
    output reg [4:0] rs2,
    output reg [4:0] shamt,
    output reg [31:0] pc_increment,

    //flags
    //00 -> no override
    //01 -> override rs1
    //10 -> override rs2
    output reg invalid_instruction
);

reg [1:0] IDU_result_counter;
reg [3:0] decryptedOPtype;
//0  -> LUI U
//1  -> AUIPC U
//2  ->  JAL J
//3  -> JALR J
//4  -> B
//5  -> S
//6  -> IG1 (load)
//7  -> IG2 (calc)
//8  -> R
//9  -> fence/fence.i
//10  -> ecall/ebreak
//11 -> invalid
//12 -> initial

always@(posedge soc_clk or posedge IDU_reset) begin
    if(IDU_reset) begin
        decryptedOPtype <= 12;
        imm <= 32'bz;
        rd <= 5'bz;
        rs1 <= 5'bz;
        rs2 <= 5'bz;
        shamt <= 5'bz;
        pc_increment <= 4;
        Instruction_to_CU <= 0;
        invalid_instruction <= 0;
    end
    else begin
        case(stage_counter)
            0: //recieve data
                begin end

            1: //decode broad type
                case(instruction[6:0]) //optype classification
                    7'b0110111: decryptedOPtype <= 0;
                    7'b0010111: decryptedOPtype <= 1;
                    7'b1101111: decryptedOPtype <= 2;
                    7'b1100111: decryptedOPtype <= 3;
                    7'b1100011: decryptedOPtype <= 4;
                    7'b0100011: decryptedOPtype <= 5;
                    7'b0000011: decryptedOPtype <= 6;
                    7'b0010011: decryptedOPtype <= 7;
                    7'b0110011: decryptedOPtype <= 8;
                    7'b0001111: decryptedOPtype <= 9; //fence
                    7'b1110011: decryptedOPtype <= 10; //ecall/ebreak
                    default: decryptedOPtype <= 11; //error case
                endcase


            2: //decode specific type and write to output
                case(decryptedOPtype)
                    4'd0: begin //LUI U
                        imm <= {instruction[31:12], {12{1'b0}}};
                        rd <= instruction[11:7];
                        rs1 <= 5'bz;
                        rs2 <= 5'bz;
                        shamt <= 5'bz;
                        pc_increment <= 4;
                        Instruction_to_CU <= 0;
                        invalid_instruction <= 0;
                    end
                    4'd1: begin//AUIPC U
                        imm <= {instruction[31:12], {12{1'b0}}};
                        rd <= instruction[11:7];
                        rs1 <= 5'bz;
                        rs2 <= 5'bz;
                        shamt <= 5'bz;
                        pc_increment <= 4;
                        Instruction_to_CU <= 1;
                        invalid_instruction <= 0;
                    end
                    4'd2: begin//JAL J
                        imm <= 32'b0;
                        rd <= instruction[11:7];
                        rs1 <= 5'bz;
                        rs2 <= 5'bz;
                        shamt <= 5'bz;
                        pc_increment <= {{11{instruction[31]}}, instruction[31], instruction[19:12], instruction[20], instruction[30:21],1'b0}; //note the ending with 1'b0 as jumps must be aligned to the nearest 2 bytes to accommodate for R16 instructions.
                        Instruction_to_CU <= 2;
                        invalid_instruction <= 0;
                    end
                    4'd3: begin//JALR J
                        imm <= {{20{instruction[31]}}, instruction[31:20]}; //same logic as above, but note that the lsb does not need to be 0 as rs1 + imm can both be odd and result in an even address. if it doesn't, make sure to cut off the last bit.
                        rd <= instruction[11:7];
                        rs1 <= instruction[19:15];
                        rs2 <= 5'bz;
                        shamt <= 5'bz;
                        pc_increment <= 4;
                        Instruction_to_CU <= 3;
                        invalid_instruction <= 0;
                    end
                    4'd4: begin//B
                        imm <= {{19{instruction[31]}}, instruction[31], instruction[7], instruction[30:25], instruction[11:8], 1'b0};
                        rd <= 5'bz;
                        rs1 <= instruction[19:15];
                        rs2 <= instruction[24:20];
                        shamt <= 5'bz;
                        pc_increment <= 4;
                        invalid_instruction <= 0;
                        case(instruction[14:12])
                            3'b000: Instruction_to_CU <= 4; //beq
                            3'b001: Instruction_to_CU <= 5; //bne
                            3'b100: Instruction_to_CU <= 6; //blt
                            3'b101: Instruction_to_CU <= 7; //bge
                            3'b110: Instruction_to_CU <= 8; //bltu
                            3'b111: Instruction_to_CU <= 9; //bgeu
                            default: invalid_instruction <= 1;
                        endcase
                    end
                    4'd5: begin//S
                        imm <= {{20{instruction[31]}}, instruction[31], instruction[30:25], instruction[11:7]};
                        rd <= 5'bz;
                        rs1 <= instruction[19:15];
                        rs2 <= instruction[24:20];
                        shamt <= 5'bz;
                        pc_increment <= 4;
                        invalid_instruction <= 0;
                        case(instruction[14:12])
                            3'b000: Instruction_to_CU <= 10; //sb
                            3'b001: Instruction_to_CU <= 11; //sh
                            3'b010: Instruction_to_CU <= 12; //sw
                            default: invalid_instruction <= 1;
                        endcase
                    end
                    4'd6: begin//IG1 I (load)
                        imm <= {{20{instruction[31]}}, instruction[31:20]};
                        rd <= instruction[11:7];
                        rs1 <= instruction[19:15];
                        rs2 <= 5'bz;
                        shamt <= 5'bz;
                        pc_increment <= 4;
                        invalid_instruction <= 0;
                        case(instruction[14:12])
                            3'b000: Instruction_to_CU <= 13; //lb
                            3'b001: Instruction_to_CU <= 14; //lh
                            3'b010: Instruction_to_CU <= 15; //lw
                            3'b100: Instruction_to_CU <= 16; //lbu
                            3'b101: Instruction_to_CU <= 17; //lhu
                            default: invalid_instruction <= 1;
                        endcase
                    end
                    4'd7: begin//IG2 I (calc)
                        rd <= instruction[11:7];
                        rs1 <= instruction[19:15];
                        rs2 <= 5'bz;
                        pc_increment <= 4;
                        invalid_instruction <= 0;
                        case(instruction[14:12])
                            3'b000: begin //addi
                                Instruction_to_CU <= 18; 
                                imm <= {{20{instruction[31]}}, instruction[31:20]};
                                shamt <= 5'bz;
                            end
                            3'b010: begin //slti
                                Instruction_to_CU <= 19; 
                                imm <= {{20{instruction[31]}}, instruction[31:20]};
                                shamt <= 5'bz;
                            end
                            3'b011: begin //sltiu
                                Instruction_to_CU <= 20; 
                                imm <= {{20{instruction[31]}}, instruction[31:20]};
                                shamt <= 5'bz;
                            end
                            3'b100: begin //xori
                                Instruction_to_CU <= 21;
                                imm <= {{20{instruction[31]}}, instruction[31:20]};
                                shamt <= 5'bz;
                            end
                            3'b110: begin //ori
                                Instruction_to_CU <= 22;
                                imm <= {{20{instruction[31]}}, instruction[31:20]};
                                shamt <= 5'bz;
                            end
                            3'b111: begin //andi
                                Instruction_to_CU <= 23;
                                imm <= {{20{instruction[31]}}, instruction[31:20]};
                                shamt <= 5'bz;
                            end


                            3'b001: begin
                                Instruction_to_CU <= 24;
                                imm <= 32'bz;
                                shamt <= instruction[24:20];
                            end

                            3'b101: begin
                                if(!instruction[30]) begin
                                    Instruction_to_CU <= 25;
                                    imm <= 32'bz;
                                    shamt <= instruction[24:20];
                                end else begin
                                    Instruction_to_CU <= 26;
                                    imm <= 32'bz;
                                    shamt <= instruction[24:20];
                                end
                            end

                            default: invalid_instruction <= 1;
                        endcase
                    end

                    4'd8: begin//R
                        imm <= 32'bz;
                        rd <= instruction[11:7];
                        rs1 <= instruction[19:15];
                        rs2 <= instruction[24:20];
                        shamt <= 5'bz;
                        pc_increment <= 4;
                        invalid_instruction <= 0;
                        case(instruction[14:12])
                            3'b000: begin
                                if(!instruction[30]) begin //add
                                    Instruction_to_CU <= 27;
                                end else begin //sub
                                    Instruction_to_CU <= 28;
                                end
                            end
                            3'b001: Instruction_to_CU <= 29; //sll
                            3'b010: Instruction_to_CU <= 30; //slt
                            3'b011: Instruction_to_CU <= 31; //sltu
                            3'b100: Instruction_to_CU <= 32; //xor
                            3'b101: begin 
                                if(!instruction[30]) begin //srl
                                    Instruction_to_CU <= 33;
                                end else begin //sra
                                    Instruction_to_CU <= 34;
                                end
                            end
                            3'b110: Instruction_to_CU <= 35; //or
                            3'b111: Instruction_to_CU <= 36; //and
                            default: invalid_instruction <= 1;
                        endcase
                    end
                    4'd9: begin//FENCE/FENCE.I
                        imm <= 32'bz;
                        rd <= 5'bz;
                        rs1 <= 5'bz;
                        rs2 <= 5'bz;
                        shamt <= 5'bz;
                        pc_increment <= 4;
                        invalid_instruction <= 0;
                        case(instruction[14:12])
                            3'b000: Instruction_to_CU <= 37; //fence
                            3'b001: Instruction_to_CU <= 38; //fence.i
                            default: invalid_instruction <= 1;
                        endcase
                    end
                    4'd10: begin//ECALL/EBREAK
                        case(instruction[20])
                            1'b0: begin
                                Instruction_to_CU <= 39; //ecall
                                decryptedOPtype <= 12;
                                imm <= 32'bz;
                                rd <= 5'bz;
                                rs1 <= 5'bz;
                                rs2 <= 5'bz;
                                shamt <= 5'bz;
                                pc_increment <= 4;
                                invalid_instruction <= 0;
                            end
                            1'b1: Instruction_to_CU <= 40; //ebreak means no reset
                        endcase
                    end

                   // 4'd12: begin//INITIALIZED
                   //     imm <= 32'bz;
                   //     rd <= 5'bz;
                   //     rs1 <= 5'bz;
                   //     rs2 <= 5'bz;
                   //     shamt <= 5'bz;
                   //     pc_increment <= 4;
                   //     invalid_instruction <= 0;
                   // end

                    default: begin //ERROR. should catch 11 case
                        $finish;
                    end
                endcase

            3: //no operation
                begin end
        endcase
    end
end

endmodule

Testbench/IDU_TB/tb_idu.sv
/// NO LONGER WORKS DUE TO MOVING STAGE COUNTER TO CU. need to generate new stimulus with using new instantiation


`timescale 1ns/1ps

module tb_idu;

    //----------------------------------------------------------------
    // Signal Declarations
    //----------------------------------------------------------------
    reg soc_clk;
    reg IDU_reset;
    reg [31:0] instruction;

    // Outputs from DUT
    wire [4:0] Instruction_to_ALU;
    wire [5:0] Instruction_to_CU;
    wire [31:0] imm;
    wire [4:0] rd;
    wire [4:0] rs1;
    wire [4:0] rs2;
    wire [4:0] shamt;
    wire [31:0] pc_increment;
    wire invalid_instruction;
    reg [1:0] stage_counter;

    // Testbench variables
    integer tests_passed = 0;
    integer tests_failed = 0;

    //----------------------------------------------------------------
    // DUT Instantiation
    //----------------------------------------------------------------
    IDU_top DUT (
        .soc_clk(soc_clk),
        .IDU_reset(IDU_reset),
        .instruction(instruction),
        .stage_counter(stage_counter),
        .Instruction_to_CU(Instruction_to_CU),
        .imm(imm),
        .rd(rd),
        .rs1(rs1),
        .rs2(rs2),
        .shamt(shamt),
        .pc_increment(pc_increment),
        .invalid_instruction(invalid_instruction)
    );

    //----------------------------------------------------------------
    // Clock Generation
    //----------------------------------------------------------------
    initial begin
        soc_clk = 0;
        forever #5 soc_clk = ~soc_clk; // 100MHz
    end

    //----------------------------------------------------------------
    // Test Task
    //----------------------------------------------------------------
    task check_op;
        input string name;
        input [31:0] instr_in;
        input [5:0] exp_cu_op;
        input [4:0] exp_rd;
        input [4:0] exp_rs1;
        input [4:0] exp_rs2;
        input [31:0] exp_imm;
        input check_imm; // 1 to check imm, 0 to expect Z
    begin
        // 1. Apply Instruction
        instruction = instr_in;
        
        // 2. Wait for IDU State Machine
        // Cycle 0: Receive (Counter 0)
        // Cycle 1: Broad Decode (Counter 1)
        // Cycle 2: Specific Decode & Output (Counter 2) -> Check here
        
        // Wait 2 clock edges to get to state 2 logic
        repeat(2) @(posedge soc_clk);
        
        // Allow combinatorial logic to settle after the 2nd edge
        #1; 

        // 3. Verify Outputs
        if (Instruction_to_CU === exp_cu_op &&
            rd === exp_rd &&
            rs1 === exp_rs1 &&
            (rs2 === exp_rs2) && // Use === for Z comparison
            (!check_imm || imm === exp_imm)) begin
            
            $display("[PASS] %s | Inst: %h | CU_OP: %d", name, instr_in, Instruction_to_CU);
            tests_passed++;
        end else begin
            $display("[FAIL] %s | Inst: %h", name, instr_in);
            if (Instruction_to_CU !== exp_cu_op) $display("\tExp CU: %d, Got: %d", exp_cu_op, Instruction_to_CU);
            if (rd !== exp_rd) $display("\tExp RD: %h, Got: %h", exp_rd, rd);
            if (rs1 !== exp_rs1) $display("\tExp RS1: %h, Got: %h", exp_rs1, rs1);
            if (rs2 !== exp_rs2) $display("\tExp RS2: %h, Got: %h", exp_rs2, rs2);
            if (check_imm && imm !== exp_imm) $display("\tExp IMM: %h, Got: %h", exp_imm, imm);
            tests_failed++;
        end

        // Wait for cycle 3 (No Op) and wrap around
        repeat(2) @(posedge soc_clk);
    end
    endtask

    //----------------------------------------------------------------
    // Main Test Sequence
    //----------------------------------------------------------------
    // Drive stage_counter synchronously; avoid zero-delay forever loops
    always @(posedge soc_clk or posedge IDU_reset) begin
        if (IDU_reset) begin
            stage_counter <= 0;
        end else begin
            stage_counter <= stage_counter + 1;
        end
    end
    
    initial begin
        // Initialize
        IDU_reset = 1;
        instruction = 0;
        #20;
        IDU_reset = 0;
        #10;

        $display("=== Starting IDU Verification ===");

        // --- Type 0: LUI (CU Code 0) ---
        // LUI x1, 0x12345 -> Imm=0x12345000
        check_op("LUI", 32'h123450B7, 6'd0, 5'd1, 5'bz, 5'bz, 32'h12345000, 1);

        // --- Type 1: AUIPC (CU Code 1) ---
        // AUIPC x2, 0x10000
        check_op("AUIPC", 32'h10000117, 6'd1, 5'd2, 5'bz, 5'bz, 32'h10000000, 1);

        // --- Type 2: JAL (CU Code 2) ---
        // JAL x1, offset -> J-Type
        // 000000000001 00000 000 00001 1101111 (JAL x1, 1) -> Imm decoding is complex
        check_op("JAL", 32'h001000EF, 6'd2, 5'd1, 5'bz, 5'bz, 32'h0, 0); // Imm is 0 in your code for JAL

        // --- Type 3: JALR (CU Code 3) ---
        // JALR x1, x2, 0
        check_op("JALR", 32'h000100E7, 6'd3, 5'd1, 5'd2, 5'bz, 32'h0, 1);

        // --- Type 4: Branch (BEQ - CU Code 4) ---
        // BEQ x1, x2, offset
        check_op("BEQ", 32'h00208063, 6'd4, 5'bz, 5'd1, 5'd2, 32'h0, 0); // Checking op/regs only

        // --- Type 5: Store (SW - CU Code 12) ---
        // SW x2, 0(x1) -> funct3=010
        check_op("SW", 32'h0020A023, 6'd12, 5'bz, 5'd1, 5'd2, 32'h0, 1);

        // --- Type 6: Load (LW - CU Code 15) ---
        // LW x1, 0(x2) -> funct3=010
        check_op("LW", 32'h00012083, 6'd15, 5'd1, 5'd2, 5'bz, 32'h0, 1);

        // --- Type 7: Calc Imm (ADDI - CU Code 18) ---
        // ADDI x1, x2, 1 -> funct3=000
        check_op("ADDI", 32'h00110093, 6'd18, 5'd1, 5'd2, 5'bz, 32'h1, 1);

        // --- Type 8: Register (ADD - CU Code 27) ---
        // ADD x1, x2, x3 -> funct3=000, funct7=0000000
        check_op("ADD", 32'h003100B3, 6'd27, 5'd1, 5'd2, 5'd3, 32'bz, 0);

        // --- Type 8: Register (SUB - CU Code 28) ---
        // SUB x1, x2, x3 -> funct3=000, funct7=0100000
        check_op("SUB", 32'h403100B3, 6'd28, 5'd1, 5'd2, 5'd3, 32'bz, 0);

        // --- Type 9: FENCE (CU Code 37) ---
        check_op("FENCE", 32'h0000000F, 6'd37, 5'bz, 5'bz, 5'bz, 32'bz, 0);

        // --- Type 10: ECALL (CU Code 39) ---
        // Note: This might fail or behave oddly due to the 'instruction = 0' bug in DUT
        check_op("ECALL", 32'h00000073, 6'd39, 5'bz, 5'bz, 5'bz, 32'bz, 0);

        $display("==================================");
        $display("Tests Passed: %d", tests_passed);
        $display("Tests Failed: %d", tests_failed);
        $display("==================================");
        $finish;
    end

    //----------------------------------------------------------------
    // Waveform Generation
    //----------------------------------------------------------------
    initial begin
        $dumpfile("idu_wave.vcd"); // Specifies the output file name
        $dumpvars(0, tb_idu);
    end

endmodule

Testbench/idu_wave.vcd
$date
	Thu Jan 08 11:58:10 2026
$end
$version
	Icarus Verilog
$end
$timescale
	1ps
$end
$scope module tb_idu $end
$var wire 5 ! shamt [4:0] $end
$var wire 5 " rs2 [4:0] $end
$var wire 5 # rs1 [4:0] $end
$var wire 5 $ rd [4:0] $end
$var wire 32 % pc_increment [31:0] $end
$var wire 1 & invalid_instruction $end
$var wire 32 ' imm [31:0] $end
$var wire 6 ( Instruction_to_CU [5:0] $end
$var reg 1 ) IDU_reset $end
$var reg 32 * instruction [31:0] $end
$var reg 1 + soc_clk $end
$var reg 2 , stage_counter [1:0] $end
$var integer 32 - tests_failed [31:0] $end
$var integer 32 . tests_passed [31:0] $end
$scope module DUT $end
$var wire 1 ) IDU_reset $end
$var wire 32 / instruction [31:0] $end
$var wire 1 + soc_clk $end
$var wire 2 0 stage_counter [1:0] $end
$var reg 6 1 Instruction_to_CU [5:0] $end
$var reg 4 2 decryptedOPtype [3:0] $end
$var reg 32 3 imm [31:0] $end
$var reg 1 & invalid_instruction $end
$var reg 32 4 pc_increment [31:0] $end
$var reg 5 5 rd [4:0] $end
$var reg 5 6 rs1 [4:0] $end
$var reg 5 7 rs2 [4:0] $end
$var reg 5 8 shamt [4:0] $end
$upscope $end
$scope task check_op $end
$var reg 1 9 check_imm $end
$var reg 6 : exp_cu_op [5:0] $end
$var reg 32 ; exp_imm [31:0] $end
$var reg 5 < exp_rd [4:0] $end
$var reg 5 = exp_rs1 [4:0] $end
$var reg 5 > exp_rs2 [4:0] $end
$var reg 32 ? instr_in [31:0] $end
$upscope $end
$upscope $end
$enddefinitions $end
$comment Show the parameter values. $end
$dumpall
$end
#0
$dumpvars
bx ?
bx >
bx =
bx <
bx ;
bx :
x9
bz 8
bz 7
bz 6
bz 5
b100 4
bz 3
b1100 2
b0 1
b0 0
b0 /
b0 .
b0 -
b0 ,
0+
b0 *
1)
b0 (
bz '
0&
b100 %
bz $
bz #
bz "
bz !
$end
#5000
1+
#10000
0+
#15000
1+
#20000
0+
0)
#25000
b1 ,
b1 0
1+
#30000
0+
b10010001101000101000010110111 *
b10010001101000101000010110111 /
19
b10010001101000101000000000000 ;
bz >
bz =
b1 <
b0 :
b10010001101000101000010110111 ?
#35000
b0 2
b10 ,
b10 0
1+
#40000
0+
#45000
b11 ,
b11 0
b1 $
b1 5
b10010001101000101000000000000 '
b10010001101000101000000000000 3
1+
#46000
b1 .
#50000
0+
#55000
b0 ,
b0 0
1+
#60000
0+
#65000
b1 ,
b1 0
b10000000000000000000100010111 *
b10000000000000000000100010111 /
b10000000000000000000000000000 ;
b10 <
b1 :
b10000000000000000000100010111 ?
1+
#70000
0+
#75000
b1 2
b10 ,
b10 0
1+
#80000
0+
#85000
b11 ,
b11 0
b1 (
b1 1
b10 $
b10 5
b10000000000000000000000000000 '
b10000000000000000000000000000 3
1+
#86000
b10 .
#90000
0+
#95000
b0 ,
b0 0
1+
#100000
0+
#105000
b1 ,
b1 0
b100000000000011101111 *
b100000000000011101111 /
09
b0 ;
b1 <
b10 :
b100000000000011101111 ?
1+
#110000
0+
#115000
b10 2
b10 ,
b10 0
1+
#120000
0+
#125000
b11 ,
b11 0
b10 (
b10 1
b100000000000 %
b100000000000 4
b1 $
b1 5
b0 '
b0 3
1+
#126000
b11 .
#130000
0+
#135000
b0 ,
b0 0
1+
#140000
0+
#145000
b1 ,
b1 0
b10000000011100111 *
b10000000011100111 /
19
b10 =
b11 :
b10000000011100111 ?
1+
#150000
0+
#155000
b11 2
b10 ,
b10 0
1+
#160000
0+
#165000
b11 ,
b11 0
b11 (
b11 1
b100 %
b100 4
b10 #
b10 6
1+
#166000
b100 .
#170000
0+
#175000
b0 ,
b0 0
1+
#180000
0+
#185000
b1 ,
b1 0
b1000001000000001100011 *
b1000001000000001100011 /
09
b10 >
b1 =
bz <
b100 :
b1000001000000001100011 ?
1+
#190000
0+
#195000
b100 2
b10 ,
b10 0
1+
#200000
0+
#205000
b11 ,
b11 0
b100 (
b100 1
b10 "
b10 7
b1 #
b1 6
bz $
bz 5
1+
#206000
b101 .
#210000
0+
#215000
b0 ,
b0 0
1+
#220000
0+
#225000
b1 ,
b1 0
b1000001010000000100011 *
b1000001010000000100011 /
19
b1100 :
b1000001010000000100011 ?
1+
#230000
0+
#235000
b101 2
b10 ,
b10 0
1+
#240000
0+
#245000
b11 ,
b11 0
b1100 (
b1100 1
1+
#246000
b110 .
#250000
0+
#255000
b0 ,
b0 0
1+
#260000
0+
#265000
b1 ,
b1 0
b10010000010000011 *
b10010000010000011 /
bz >
b10 =
b1 <
b1111 :
b10010000010000011 ?
1+
#270000
0+
#275000
b110 2
b10 ,
b10 0
1+
#280000
0+
#285000
b11 ,
b11 0
b1111 (
b1111 1
bz "
bz 7
b10 #
b10 6
b1 $
b1 5
1+
#286000
b111 .
#290000
0+
#295000
b0 ,
b0 0
1+
#300000
0+
#305000
b1 ,
b1 0
b100010000000010010011 *
b100010000000010010011 /
b1 ;
b10010 :
b100010000000010010011 ?
1+
#310000
0+
#315000
b111 2
b10 ,
b10 0
1+
#320000
0+
#325000
b11 ,
b11 0
b1 '
b1 3
b10010 (
b10010 1
1+
#326000
b1000 .
#330000
0+
#335000
b0 ,
b0 0
1+
#340000
0+
#345000
b1 ,
b1 0
b1100010000000010110011 *
b1100010000000010110011 /
09
bz ;
b11 >
b11011 :
b1100010000000010110011 ?
1+
#350000
0+
#355000
b1000 2
b10 ,
b10 0
1+
#360000
0+
#365000
b11 ,
b11 0
b11011 (
b11011 1
b11 "
b11 7
bz '
bz 3
1+
#366000
b1001 .
#370000
0+
#375000
b0 ,
b0 0
1+
#380000
0+
#385000
b1 ,
b1 0
b1000000001100010000000010110011 *
b1000000001100010000000010110011 /
b11100 :
b1000000001100010000000010110011 ?
1+
#390000
0+
#395000
b10 ,
b10 0
1+
#400000
0+
#405000
b11 ,
b11 0
b11100 (
b11100 1
1+
#406000
b1010 .
#410000
0+
#415000
b0 ,
b0 0
1+
#420000
0+
#425000
b1 ,
b1 0
b1111 *
b1111 /
bz >
bz =
bz <
b100101 :
b1111 ?
1+
#430000
0+
#435000
b1001 2
b10 ,
b10 0
1+
#440000
0+
#445000
b11 ,
b11 0
b100101 (
b100101 1
bz "
bz 7
bz #
bz 6
bz $
bz 5
1+
#446000
b1011 .
#450000
0+
#455000
b0 ,
b0 0
1+
#460000
0+
#465000
b1 ,
b1 0
b1110011 *
b1110011 /
b100111 :
b1110011 ?
1+
#470000
0+
#475000
b1010 2
b10 ,
b10 0
1+
#480000
0+
#485000
b11 ,
b11 0
b1100 2
b100111 (
b100111 1
1+
#486000
b1100 .
#490000
0+
#495000
b0 ,
b0 0
1+
#500000
0+
#505000
b1 ,
b1 0
1+
