SRAM/SRAM_sim.sv
//SRAM used for simulation due to ease of not needing to debug 4000 separate modules for individual bits. Attempt to match the behavior of SRAM.

module SRAM_sim(
    input  logic        clk,
    input  logic        reset,
    input  logic [6:0]  addr_sel,
    input  logic [3:0]  byte_sel,
    input  logic        read_enable,    // synchronous read enable
    input  logic        write_enable,   // synchronous write enable
    input  logic [31:0] datain,
    output wire [31:0] dataout
);

    reg [31:0] memory [127:0];
    reg [31:0] reg_dataout;
    reg read_valid;


    integer i;

    initial begin
        for (i = 0; i < 128; i = i + 1) begin
            memory[i] = 32'b0;
        end
    end

    // Drive WL_sel and byte selection synchronously
    always @(posedge clk) begin
        if (reset) begin            
        end else begin
            if (write_enable && read_enable) begin
            end
            else if (write_enable) begin
                if(byte_sel[0]==1) begin
                    memory[addr_sel][7:0] <= datain[7:0];
                end

                if(byte_sel[1]==1) begin
                    memory[addr_sel][15:8] <= datain[15:8];
                end

                if(byte_sel[2]==1) begin
                    memory[addr_sel][23:16] <= datain[23:16];
                end
                
                if(byte_sel[3]==1) begin
                    memory[addr_sel][31:24] <= datain[31:24];
                end
            end
            else if (read_enable) begin //partial reads are not supported, only partial writes
                reg_dataout <= memory[addr_sel];
                read_valid  <= 1'b1;
            end
        end
    end
    
assign dataout = (reset || !read_valid) ? 32'b0 : reg_dataout;


endmodule

Modules/MMU.sv
module MMU(
    input soc_clk,
    input reset,

    // FROM CU
    input [6:0] CU_address,   // byte address
    input [3:0]  CU_bytesel,   // byte enables
    input [31:0] CU_dat_in,
    input        read_or_write, // 0 = read, 1 = write
    input        retrieve,      // start memory op (pulse)

    // TO CU
    output reg [31:0] MMU_dat_out
);

    // --------------------------------------------
    // Internal SRAM signals
    // --------------------------------------------
    reg         read_pulse;
    reg         write_pulse;
    reg  [31:0] SRAM_dat_in;

    // --------------------------------------------
    // SRAM instance
    // --------------------------------------------
    SRAM_sim sram_inst (
        .clk(soc_clk),
        .reset(reset),
        .addr_sel   (CU_address),
        .byte_sel   (CU_bytesel),
        .read_enable (read_pulse),
        .write_enable(write_pulse),
        .datain     (SRAM_dat_in),
        .dataout    (MMU_dat_out)
    );

    // --------------------------------------------
    // MMU control FSM (stub for now)
    // --------------------------------------------
    always @(posedge soc_clk) begin
        if (reset) begin
            write_pulse <= 0;
            read_pulse <= 0;
            SRAM_dat_in <= 0;
        end
        else begin
            SRAM_dat_in <= CU_dat_in;
            if(retrieve) begin
                if(read_or_write==1) begin //write
                    write_pulse <= 1;
                    read_pulse <= 0;
                end
                else begin //read
                    write_pulse <= 0;
                    read_pulse <= 1;
                end
            end
            else begin
                write_pulse <= 0;
                read_pulse <= 0;
            end
        end
    end

endmodule

Testbench/MMU_TB/tb_mmu.sv
`timescale 1ns/1ps

module tb_MMU;

    // Parameters
    localparam DATA_WIDTH = 32;

    // Signals
    logic clk;
    logic reset;
    
    // MMU Interface Signals
    logic [6:0] CU_address;
    logic [3:0]  CU_bytesel;
    logic [31:0] CU_dat_in;
    logic        read_or_write; // 0 = read, 1 = write
    logic        retrieve;      // start op pulse
    
    wire [31:0] MMU_dat_out;

    // Instantiate DUT
    MMU dut (
        .soc_clk(clk),
        .reset(reset),
        .CU_address(CU_address),
        .CU_bytesel(CU_bytesel),
        .CU_dat_in(CU_dat_in),
        .read_or_write(read_or_write),
        .retrieve(retrieve),
        .MMU_dat_out(MMU_dat_out)
    );

    // Clock Generation
    initial begin
        clk = 0;
        forever #5 clk = ~clk; // 100 MHz
    end

    // VCD Dump
    initial begin
        $dumpfile("mmu_wave.vcd");
        $dumpvars(0, tb_MMU);
    end

    // Helper Tasks
    task automatic write_word(
        input logic [6:0] addr,
        input logic [31:0] data, 
        input logic [3:0]  mask
    );
        begin
            @(posedge clk);
            CU_address = addr;
            CU_dat_in = data;
            CU_bytesel = mask;
            read_or_write = 1; // Write
            retrieve = 1;      // Start

            @(posedge clk);
            
            @(posedge clk);
            retrieve = 0;      // Pulse off
            
            // Allow time for internal SRAM pulse generation and write
            repeat(2) @(posedge clk);
        end
    endtask

    task automatic read_word(
        input logic [6:0] addr, 
        input logic [31:0] expected
    );
        begin
            @(posedge clk);
            CU_address = addr;
            CU_bytesel = 4'b1111; // Read full word
            read_or_write = 0;    // Read
            retrieve = 1;         // Start

            // Wait for data to propagate out
            repeat(2) @(posedge clk);

            if (MMU_dat_out !== expected) begin
                $display("ERROR  @ Addr %0h: Expected %h, Got %h", addr, expected, MMU_dat_out);
            end else begin
                $display("PASSED @ Addr %0h: Got %h", addr, MMU_dat_out);
            end
            retrieve = 0;
        end
    endtask

    // Main Test Sequence
    initial begin
        // Initialize Inputs
        CU_address = 0;
        CU_bytesel = 0;
        CU_dat_in = 0;
        read_or_write = 0;
        retrieve = 0;
        reset = 1;


        // Reset Wait
        repeat(5) @(posedge clk);
        reset = 0;
        #10;

        $display("=== Starting MMU Test ===");

        // 1. Basic Read/Write Test
        write_word(7'd0, 32'hDEADBEEF, 4'b1111);
        write_word(7'd1, 32'hCAFEBABE, 4'b1111);
        
        read_word(7'd0, 32'hDEADBEEF);
        read_word(7'd1, 32'hCAFEBABE);

        // 2. Byte Select Write Test
        // Write 0xFFFFFFFF
        write_word(7'd2, 32'hFFFFFFFF, 4'b1111);
        // Overwrite only lower byte with 0x00
        write_word(7'd2, 32'h00000000, 4'b0001);
        // Expect 0xFFFFFF00
        read_word(7'd2, 32'hFFFFFF00);

        // 3. Overlapping Regions Test
        // Write 0xAAAAAAAA to address 0
        write_word(7'd0, 32'hAAAAAAAA, 4'b1111);
        // Write 0x55555555 to address 2 (overlaps with previous)
        write_word(7'd2, 32'h55555555, 4'b1111);
        
        // Read back the overlapped region
        read_word(7'd0, 32'hAAAAAAAA);
        read_word(7'd2, 32'h55555555);

        // 4. Sequential Access Test
        // Write sequential words
        for (int i = 0; i < 4; i++) begin
            write_word(32'd10 + i, 32'hA5A5A5A5, 4'b1111);
        end
        
        // Read them back
        for (int i = 0; i < 4; i++) begin
            read_word(32'd10 + i, 32'hA5A5A5A5);
        end

        $display("=== MMU Test Completed ===");
        $finish;
    end

endmodule

Testbench/mmu_wave.vcd
$date
	Tue Jan 06 17:41:35 2026
$end
$version
	Icarus Verilog
$end
$timescale
	1ps
$end
$scope module tb_MMU $end
$var wire 32 ! MMU_dat_out [31:0] $end
$var parameter 32 " DATA_WIDTH $end
$var reg 7 # CU_address [6:0] $end
$var reg 4 $ CU_bytesel [3:0] $end
$var reg 32 % CU_dat_in [31:0] $end
$var reg 1 & clk $end
$var reg 1 ' read_or_write $end
$var reg 1 ( reset $end
$var reg 1 ) retrieve $end
$scope module dut $end
$var wire 7 * CU_address [6:0] $end
$var wire 4 + CU_bytesel [3:0] $end
$var wire 32 , CU_dat_in [31:0] $end
$var wire 1 ' read_or_write $end
$var wire 1 ( reset $end
$var wire 1 ) retrieve $end
$var wire 1 & soc_clk $end
$var wire 32 - MMU_dat_out [31:0] $end
$var reg 32 . SRAM_dat_in [31:0] $end
$var reg 1 / read_pulse $end
$var reg 1 0 write_pulse $end
$scope module sram_inst $end
$var wire 7 1 addr_sel [6:0] $end
$var wire 4 2 byte_sel [3:0] $end
$var wire 1 & clk $end
$var wire 32 3 datain [31:0] $end
$var wire 1 / read_enable $end
$var wire 1 ( reset $end
$var wire 1 0 write_enable $end
$var wire 32 4 dataout [31:0] $end
$var reg 1 5 read_valid $end
$var reg 32 6 reg_dataout [31:0] $end
$var integer 32 7 i [31:0] $end
$upscope $end
$upscope $end
$scope begin $ivl_for_loop0 $end
$var integer 32 8 i [31:0] $end
$upscope $end
$scope begin $ivl_for_loop1 $end
$var integer 32 9 i [31:0] $end
$upscope $end
$scope task read_word $end
$upscope $end
$scope task write_word $end
$upscope $end
$upscope $end
$enddefinitions $end
$comment Show the parameter values. $end
$dumpall
b100000 "
$end
#0
$dumpvars
b0 9
b0 8
b10000000 7
bx 6
x5
b0 4
bx 3
b0 2
b0 1
x0
x/
bx .
b0 -
b0 ,
b0 +
b0 *
0)
1(
0'
0&
b0 %
b0 $
b0 #
b0 !
$end
#5000
b0 .
b0 3
0/
00
1&
#10000
0&
#15000
1&
#20000
0&
#25000
1&
#30000
0&
#35000
1&
#40000
0&
#45000
bx !
bx -
bx 4
0(
1&
#50000
0&
#55000
10
b11011110101011011011111011101111 .
b11011110101011011011111011101111 3
1)
1'
b1111 $
b1111 +
b1111 2
b11011110101011011011111011101111 %
b11011110101011011011111011101111 ,
1&
#60000
0&
#65000
1&
#70000
0&
#75000
00
0)
1&
#80000
0&
#85000
1&
#90000
0&
#95000
1&
#100000
0&
#105000
10
b11001010111111101011101010111110 .
b11001010111111101011101010111110 3
1)
b11001010111111101011101010111110 %
b11001010111111101011101010111110 ,
b1 #
b1 *
b1 1
1&
#110000
0&
#115000
1&
#120000
0&
#125000
00
0)
1&
#130000
0&
#135000
1&
#140000
0&
#145000
1&
#150000
0&
#155000
1/
1)
0'
b0 #
b0 *
b0 1
1&
#160000
0&
#165000
b11011110101011011011111011101111 !
b11011110101011011011111011101111 -
b11011110101011011011111011101111 4
15
b11011110101011011011111011101111 6
1&
#170000
0&
#175000
0/
0)
1&
#180000
0&
#185000
1/
1)
b1 #
b1 *
b1 1
1&
#190000
0&
#195000
b11001010111111101011101010111110 !
b11001010111111101011101010111110 -
b11001010111111101011101010111110 4
b11001010111111101011101010111110 6
1&
#200000
0&
#205000
0/
0)
1&
#210000
0&
#215000
10
b11111111111111111111111111111111 .
b11111111111111111111111111111111 3
1)
1'
b11111111111111111111111111111111 %
b11111111111111111111111111111111 ,
b10 #
b10 *
b10 1
1&
#220000
0&
#225000
1&
#230000
0&
#235000
00
0)
1&
#240000
0&
#245000
1&
#250000
0&
#255000
1&
#260000
0&
#265000
10
b0 .
b0 3
1)
b1 $
b1 +
b1 2
b0 %
b0 ,
1&
#270000
0&
#275000
1&
#280000
0&
#285000
00
0)
1&
#290000
0&
#295000
1&
#300000
0&
#305000
1&
#310000
0&
#315000
1/
1)
0'
b1111 $
b1111 +
b1111 2
1&
#320000
0&
#325000
b11111111111111111111111100000000 !
b11111111111111111111111100000000 -
b11111111111111111111111100000000 4
b11111111111111111111111100000000 6
1&
#330000
0&
#335000
0/
0)
1&
#340000
0&
#345000
10
b10101010101010101010101010101010 .
b10101010101010101010101010101010 3
1)
1'
b10101010101010101010101010101010 %
b10101010101010101010101010101010 ,
b0 #
b0 *
b0 1
1&
#350000
0&
#355000
1&
#360000
0&
#365000
00
0)
1&
#370000
0&
#375000
1&
#380000
0&
#385000
1&
#390000
0&
#395000
10
b1010101010101010101010101010101 .
b1010101010101010101010101010101 3
1)
b1010101010101010101010101010101 %
b1010101010101010101010101010101 ,
b10 #
b10 *
b10 1
1&
#400000
0&
#405000
1&
#410000
0&
#415000
00
0)
1&
#420000
0&
#425000
1&
#430000
0&
#435000
1&
#440000
0&
#445000
1/
1)
0'
b0 #
b0 *
b0 1
1&
#450000
0&
#455000
b10101010101010101010101010101010 !
b10101010101010101010101010101010 -
b10101010101010101010101010101010 4
b10101010101010101010101010101010 6
1&
#460000
0&
#465000
0/
0)
1&
#470000
0&
#475000
1/
1)
b10 #
b10 *
b10 1
1&
#480000
0&
#485000
b1010101010101010101010101010101 !
b1010101010101010101010101010101 -
b1010101010101010101010101010101 4
b1010101010101010101010101010101 6
1&
#490000
0&
#495000
0/
0)
1&
#500000
0&
#505000
10
b10100101101001011010010110100101 .
b10100101101001011010010110100101 3
1)
1'
b10100101101001011010010110100101 %
b10100101101001011010010110100101 ,
b1010 #
b1010 *
b1010 1
1&
#510000
0&
#515000
1&
#520000
0&
#525000
00
0)
1&
#530000
0&
#535000
1&
#540000
0&
#545000
b1 8
1&
#550000
0&
#555000
10
1)
b1011 #
b1011 *
b1011 1
1&
#560000
0&
#565000
1&
#570000
0&
#575000
00
0)
1&
#580000
0&
#585000
1&
#590000
0&
#595000
b10 8
1&
#600000
0&
#605000
10
1)
b1100 #
b1100 *
b1100 1
1&
#610000
0&
#615000
1&
#620000
0&
#625000
00
0)
1&
#630000
0&
#635000
1&
#640000
0&
#645000
b11 8
1&
#650000
0&
#655000
10
1)
b1101 #
b1101 *
b1101 1
1&
#660000
0&
#665000
1&
#670000
0&
#675000
00
0)
1&
#680000
0&
#685000
1&
#690000
0&
#695000
b100 8
1&
#700000
0&
#705000
1/
1)
0'
b1010 #
b1010 *
b1010 1
1&
#710000
0&
#715000
b10100101101001011010010110100101 !
b10100101101001011010010110100101 -
b10100101101001011010010110100101 4
b10100101101001011010010110100101 6
1&
#720000
0&
#725000
0/
b1 9
0)
1&
#730000
0&
#735000
1/
1)
b1011 #
b1011 *
b1011 1
1&
#740000
0&
#745000
1&
#750000
0&
#755000
0/
b10 9
0)
1&
#760000
0&
#765000
1/
1)
b1100 #
b1100 *
b1100 1
1&
#770000
0&
#775000
1&
#780000
0&
#785000
0/
b11 9
0)
1&
#790000
0&
#795000
1/
1)
b1101 #
b1101 *
b1101 1
1&
#800000
0&
#805000
1&
#810000
0&
#815000
0/
b100 9
0)
1&
