SRAM/SRAM_sim.sv
//SRAM used for simulation due to ease of not needing to debug 4000 separate modules for individual bits. Attempt to match the behavior of SRAM.

module SRAM_sim(
    input  logic        clk,
    input  logic        reset,
    input  logic [6:0]  addr_sel,
    input  logic [3:0]  byte_sel,
    input  logic        read_enable,    // synchronous read enable
    input  logic        write_enable,   // synchronous write enable
    input  logic [31:0] datain,
    output wire [31:0] dataout
);

    reg [31:0] memory [127:0];
    reg [31:0] reg_dataout;

    integer i;

    initial begin
        for (i = 0; i < 128; i = i + 1) begin
            memory[i] = 32'b0;
        end
    end

    // Drive WL_sel and byte selection synchronously
    always @(posedge clk) begin
        if (reset) begin            
        end else begin
            if (write_enable && read_enable) begin
            end
            else if (write_enable) begin
                if(byte_sel[0]==1) begin
                    memory[addr_sel][7:0] <= datain[7:0];
                end

                if(byte_sel[1]==1) begin
                    memory[addr_sel][15:8] <= datain[15:8];
                end

                if(byte_sel[2]==1) begin
                    memory[addr_sel][23:16] <= datain[23:16];
                end
                
                if(byte_sel[3]==1) begin
                    memory[addr_sel][31:24] <= datain[31:24];
                end
            end
            else if (read_enable) begin //partial reads are not supported, only partial writes
                reg_dataout <= memory[addr_sel];
            end
        end
    end
    
    assign dataout = reset ? 32'b0 : ~read_enable ? 32'b0 : reg_dataout;


endmodule

Testbench/SRAM_TB/tb_sram.sv
`timescale 1ns/1ps

module tb_SRAM;

    // Parameters (keep consistent with SRAM)
    localparam ADDR_WIDTH = 7;
    localparam DATA_WIDTH = 32;

    // Signals (match DUT port names)
    logic clk;
    logic reset;
    logic [ADDR_WIDTH-1:0] addr_sel;
    logic [3:0] byte_sel;
    logic read_enable;
    logic write_enable;
    logic [DATA_WIDTH-1:0] datain;
    logic [DATA_WIDTH-1:0] dataout;

    // Instantiate SRAM (see: SRAM/SRAM.sv)
    SRAM_sim dut (
        .clk(clk),
        .reset(reset),
        .addr_sel(addr_sel),
        .byte_sel(byte_sel),
        .read_enable(read_enable),
        .write_enable(write_enable),
        .datain(datain),
        .dataout(dataout)
    );

    // Clock
    initial clk = 0;
    always #5 clk = ~clk; // 100 MHz

    // VCD dump
    initial begin
        $dumpfile("sram_wave.vcd");
        $dumpvars(0, tb_SRAM);
    end

    // Helpers
    task automatic write_word(input logic [ADDR_WIDTH-1:0] a,
                              input logic [DATA_WIDTH-1:0] d,
                              input logic [3:0] be);
        begin
            // Align to clock: set signals before a posedge so SRAM latches them
            @(negedge clk);
            addr_sel   = a;
            datain     = d;
            byte_sel   = be;
            write_enable = 1;
            read_enable  = 0;
            // Wait two posedges: first posedge latches WL_sel, second performs write in SRAMcell
            @(posedge clk);
            @(posedge clk);
            write_enable = 0;
            // small settle
            @(negedge clk);
        end
    endtask

    task automatic read_word(input logic [ADDR_WIDTH-1:0] a,
                             input logic [DATA_WIDTH-1:0] expected);
        begin
            // Align to clock: set address and enable read
            @(negedge clk);
            addr_sel    = a;
            // Enable all bytes for read so non-selected bytes return stored values
            byte_sel    = 4'b1111;
            read_enable = 1;
            write_enable = 0;
            // Wait two posedges: first latches WL_sel, second allows SRAM cells to drive dataout
            @(posedge clk);
            @(posedge clk);
            // sample
            if (dataout !== expected) begin
                $display("ERROR: Read mismatch @ addr %0d: got 0x%08h expected 0x%08h", a, dataout, expected);
            end else begin
                $display("OK: addr %0d = 0x%08h", a, dataout);
            end
            read_enable = 0;
            // small settle
            @(negedge clk);
        end
    endtask

    // Byte-enable helper: compose byte mask for writes
    function logic [3:0] be_mask(input int bytes);
        logic [3:0] m;
        begin
            m = 4'b1111; // default full-word
            case (bytes)
                1: m = 4'b0001;
                2: m = 4'b0011;
                3: m = 4'b0111;
                4: m = 4'b1111;
                default: m = 4'b1111;
            endcase
            return m;
        end
    endfunction

    // Basic stimulus
    initial begin
        // init
        reset = 1;
        addr_sel = '0;
        byte_sel = 4'b1111;
        read_enable = 0;
        write_enable = 0;
        datain = '0;
        repeat (4) @(negedge clk);
        reset = 0;
        @(negedge clk);

        // Simple deterministic tests
        // Write distinct patterns and read back
        write_word(7'd0,  32'hDEADBEEF, be_mask(4));
        write_word(7'd1,  32'hCAFEBABE, be_mask(4));
        write_word(7'd2,  32'h01234567, be_mask(4));
        write_word(7'd3,  32'h89ABCDEF, be_mask(4));

        // Read and verify
        read_word(7'd0, 32'hDEADBEEF);
        read_word(7'd1, 32'hCAFEBABE);
        read_word(7'd2, 32'h01234567);
        read_word(7'd3, 32'h89ABCDEF);

        // Byte-enable partial writes
        // zero then write low byte only
        write_word(7'd10, 32'h00000000, be_mask(4));
        write_word(7'd10, 32'h000000AA, be_mask(1)); // write byte0
        read_word(7'd10, 32'h000000AA);

        // Mixed byte writes
        write_word(7'd11, 32'hFFFFFFFF, be_mask(4));
        // clear upper three bytes
        write_word(7'd11, 32'h00FFFFFF, 4'b0001); // only lowest byte enabled -> no change to upper
        // read back (expect lowest byte = 0xFF still, others 0xFF)
        read_word(7'd11, 32'hFFFFFFFF);


        $display("TB finished.");
        #100 $finish;
    end

endmodule

Testbench/SRAM_TB/sram_wave.vcd
$date
	Tue Jan 06 15:19:39 2026
$end
$version
	Icarus Verilog
$end
$timescale
	1ps
$end
$scope module tb_SRAM $end
$var wire 32 ! dataout [31:0] $end
$var parameter 32 " ADDR_WIDTH $end
$var parameter 32 # DATA_WIDTH $end
$var reg 7 $ addr_sel [6:0] $end
$var reg 4 % byte_sel [3:0] $end
$var reg 1 & clk $end
$var reg 32 ' datain [31:0] $end
$var reg 1 ( read_enable $end
$var reg 1 ) reset $end
$var reg 1 * write_enable $end
$scope function be_mask $end
$var reg 4 + m [3:0] $end
$var integer 32 , bytes [31:0] $end
$upscope $end
$scope module dut $end
$var wire 7 - addr_sel [6:0] $end
$var wire 4 . byte_sel [3:0] $end
$var wire 1 & clk $end
$var wire 32 / datain [31:0] $end
$var wire 1 ( read_enable $end
$var wire 1 ) reset $end
$var wire 1 * write_enable $end
$var wire 32 0 dataout [31:0] $end
$var reg 32 1 reg_dataout [31:0] $end
$var integer 32 2 i [31:0] $end
$upscope $end
$scope task read_word $end
$upscope $end
$scope task write_word $end
$upscope $end
$upscope $end
$enddefinitions $end
$comment Show the parameter values. $end
$dumpall
b100000 #
b111 "
$end
#0
$dumpvars
b10000000 2
bx 1
b0 0
b0 /
b1111 .
b0 -
b0 ,
bx +
0*
1)
0(
b0 '
0&
b1111 %
b0 $
b0 !
$end
#5000
1&
#10000
0&
#15000
1&
#20000
0&
#25000
1&
#30000
0&
#35000
1&
#40000
0)
0&
#45000
1&
#50000
b1111 +
b100 ,
0&
#55000
1&
#60000
1*
b11011110101011011011111011101111 '
b11011110101011011011111011101111 /
0&
#65000
1&
#70000
0&
#75000
0*
1&
#80000
0&
#85000
1&
#90000
1*
b11001010111111101011101010111110 '
b11001010111111101011101010111110 /
b1 $
b1 -
0&
#95000
1&
#100000
0&
#105000
0*
1&
#110000
0&
#115000
1&
#120000
1*
b1001000110100010101100111 '
b1001000110100010101100111 /
b10 $
b10 -
0&
#125000
1&
#130000
0&
#135000
0*
1&
#140000
0&
#145000
1&
#150000
1*
b10001001101010111100110111101111 '
b10001001101010111100110111101111 /
b11 $
b11 -
0&
#155000
1&
#160000
0&
#165000
0*
1&
#170000
0&
#175000
1&
#180000
bx !
bx 0
1(
b0 $
b0 -
0&
#185000
b11011110101011011011111011101111 !
b11011110101011011011111011101111 0
b11011110101011011011111011101111 1
1&
#190000
0&
#195000
b0 !
b0 0
0(
1&
#200000
0&
#205000
1&
#210000
b11011110101011011011111011101111 !
b11011110101011011011111011101111 0
1(
b1 $
b1 -
0&
#215000
b11001010111111101011101010111110 !
b11001010111111101011101010111110 0
b11001010111111101011101010111110 1
1&
#220000
0&
#225000
b0 !
b0 0
0(
1&
#230000
0&
#235000
1&
#240000
b11001010111111101011101010111110 !
b11001010111111101011101010111110 0
1(
b10 $
b10 -
0&
#245000
b1001000110100010101100111 !
b1001000110100010101100111 0
b1001000110100010101100111 1
1&
#250000
0&
#255000
b0 !
b0 0
0(
1&
#260000
0&
#265000
1&
#270000
b1001000110100010101100111 !
b1001000110100010101100111 0
1(
b11 $
b11 -
0&
#275000
b10001001101010111100110111101111 !
b10001001101010111100110111101111 0
b10001001101010111100110111101111 1
1&
#280000
0&
#285000
b0 !
b0 0
0(
1&
#290000
0&
#295000
1&
#300000
1*
b0 '
b0 /
b1010 $
b1010 -
0&
#305000
1&
#310000
0&
#315000
0*
1&
#320000
b1 +
b1 ,
0&
#325000
1&
#330000
1*
b1 %
b1 .
b10101010 '
b10101010 /
0&
#335000
1&
#340000
0&
#345000
0*
1&
#350000
0&
#355000
1&
#360000
b10001001101010111100110111101111 !
b10001001101010111100110111101111 0
1(
b1111 %
b1111 .
0&
#365000
b10101010 !
b10101010 0
b10101010 1
1&
#370000
0&
#375000
b0 !
b0 0
0(
1&
#380000
b1111 +
b100 ,
0&
#385000
1&
#390000
1*
b11111111111111111111111111111111 '
b11111111111111111111111111111111 /
b1011 $
b1011 -
0&
#395000
1&
#400000
0&
#405000
0*
1&
#410000
0&
#415000
1&
#420000
1*
b1 %
b1 .
b111111111111111111111111 '
b111111111111111111111111 /
0&
#425000
1&
#430000
0&
#435000
0*
1&
#440000
0&
#445000
1&
#450000
b10101010 !
b10101010 0
1(
b1111 %
b1111 .
0&
#455000
b11111111111111111111111111111111 !
b11111111111111111111111111111111 0
b11111111111111111111111111111111 1
1&
#460000
0&
#465000
b0 !
b0 0
0(
1&
